wirefracture/__init__.py
wirefracture-0.0.1.dist-info/METADATA
wirefracture-0.0.1.dist-info/WHEEL
wirefracture-0.0.1.dist-info/top_level.txt
wirefracture-0.0.1.dist-info/RECORD
