Metadata-Version: 2.4
Name: wirefracture
Version: 0.0.1
Summary: Stub package to reserve the wirefracture name
License: MIT
Requires-Python: >=3.8
